fontknife/__init__.py
fontknife/cli.py
fontknife/create_textfont.py
fontknife/custom_types.py
fontknife/generate_octo.py
fontknife/iohelpers.py
fontknife/type_helpers.py
fontknife/unicode_helpers.py
fontknife/utils.py
fontknife/commands/__init__.py
fontknife/commands/__main__.py
fontknife/commands/common.py
fontknife/commands/convert.py
fontknife/commands/emit_code.py
fontknife/formats/__init__.py
fontknife/formats/common/__init__.py
fontknife/formats/common/caching.py
fontknife/formats/common/exceptions.py
fontknife/formats/common/raster_font.py
fontknife/formats/common/spritesheet.py
fontknife/formats/common/textfont.py
fontknife/formats/readers/__init__.py
fontknife/formats/readers/bdf.py
fontknife/formats/readers/pcf.py
fontknife/formats/readers/spritesheet.py
fontknife/formats/readers/textfont.py
fontknife/formats/readers/truetype.py
fontknife/formats/writers/__init__.py
fontknife/formats/writers/spritesheet.py
fontknife/formats/writers/textfont.py
fontknife/octo/__init__.py
fontknife/previews/__init__.py
fontknife-0.1.2.dist-info/LICENSE
fontknife-0.1.2.dist-info/METADATA
fontknife-0.1.2.dist-info/WHEEL
fontknife-0.1.2.dist-info/entry_points.txt
fontknife-0.1.2.dist-info/top_level.txt
fontknife-0.1.2.dist-info/RECORD
